Metadata-Version: 1.0
Name: prob-bin-gauss-distributions
Version: 0.1
Summary: Probability distributions
Home-page: UNKNOWN
Author: UNKNOWN
Author-email: UNKNOWN
License: UNKNOWN
Platform: UNKNOWN
